<?xml version="1.0" encoding="UTF-8"?>

<method>
  <name>mergeOrgInfos</name>
  <mapping>impl/users/org/merge</mapping>
  <action>POST</action>
  <parameters>
    <parameter>
      <name>com.secondmarket.secmaster.dto.wrappers.MergeOrgsMessageWrapper</name>
      <mapped>True</mapped>
      <mappinginfo>
        <mappingtype>Parameter should be bound to the web request body [RequestBody]</mappingtype>
      </mappinginfo>
    </parameter>
  </parameters>
  <returntype>com.secondmarket.connector.common.data.MapResponse</returntype>
</method>
